unscrewed/__init__.py
unscrewed/fetcher.py
unscrewed/update_config.py
unscrewed-0.1a2.dist-info/entry_points.txt
unscrewed-0.1a2.dist-info/LICENSE
unscrewed-0.1a2.dist-info/WHEEL
unscrewed-0.1a2.dist-info/METADATA
unscrewed-0.1a2.dist-info/RECORD
