Metadata-Version: 2.1
Name: unscrewed
Version: 0.1a2
Summary: Unscrewed data packaging
Author-email: Matthew Brett <matthew.brett@gmail.com>
Classifier: License :: OSI Approved :: BSD License
Classifier: Programming Language :: Python :: 3
Requires-Dist: pooch
Requires-Dist: pyyaml
Requires-Dist: pytest ; extra == "test"
Project-URL: Home, https://github.com/matthew-brett/unscrewed
Provides-Extra: test
